sprint1.py
sprint1-0.2.dist-info/LICENSE
sprint1-0.2.dist-info/WHEEL
sprint1-0.2.dist-info/METADATA
sprint1-0.2.dist-info/RECORD
