Metadata-Version: 2.1
Name: sprint1
Version: 0.2
Summary: Calculator package!
Author-email: Audrius <audrius.naujokas@gmail.com>
Classifier: License :: OSI Approved :: MIT License
